{
	"authHost": "http://localhost",
	"authEndpoint": "/broadcasting/auth",
	"clients": [
		{
			"appId": "2152303a99d2d880",
			"key": "ab8ab2a38342ca7b273e7ca4bebe5e07"
		}
	],
	"database": "redis",
	"databaseConfig": {
		"redis": {},
		"sqlite": {
			"databasePath": "/database/laravel-echo-server.sqlite"
		}
	},
	"devMode": true,
	"host": null,
	"port": "6001",
	"protocol": "http",
	"socketio": {},
	"sslCertPath": "",
	"sslKeyPath": "",
	"sslCertChainPath": "",
	"sslPassphrase": "",
	"subscribers": {
		"http": true,
		"redis": true
	},
	"apiOriginAllow": {
		"allowCors": true,
		"allowOrigin": "http://localhost:4200",
		"allowMethods": "GET, POST, DELETE, PUT, OPTION",
		"allowHeaders": "Origin, Content-Type, X-Auth-Token, X-Requested-With, Accept, Authorization, X-CSRF-TOKEN, X-S"
	}
}